{
    "kind": "youtube#searchResult",
    "etag": "\"XpPGQXPnxQJhLgs6enD_n8JR4Qk/8-DuZgnUQtIPD1ZFeMT1q4jbVok\"",
    "id": {
        "kind": "youtube#video",
        "videoId": "HkZD4lgKPX8"
    },
    "snippet": {
        "publishedAt": "2019-05-09T18:55:02.000Z",
        "channelId": "UCBR8-60-B28hp2BmDPdntcQ",
        "title": "Assumptions About Me | YouTube Creator Summit Edition",
        "description": "Think you know everything about your favorite YouTube creators? We asked for your assumptions, now watch and find out if they're true. #CreatorSummit For ...",
        "thumbnails": {
            "default": {
                "url": "https://i.ytimg.com/vi/HkZD4lgKPX8/default.jpg",
                "width": 120,
                "height": 90
            },
            "medium": {
                "url": "https://i.ytimg.com/vi/HkZD4lgKPX8/mqdefault.jpg",
                "width": 320,
                "height": 180
            },
            "high": {
                "url": "https://i.ytimg.com/vi/HkZD4lgKPX8/hqdefault.jpg",
                "width": 480,
                "height": 360
            }
        },
        "channelTitle": "YouTube",
        "liveBroadcastContent": "none"
    }
}
